[
  {
    "id": "NBVf17d",
    "title": null,
    "description": null,
    "type": "image/jpeg",
    "width": 4608,
    "height": 3456,
    "size": 3096924,
    "account_url": null,
    "account_id": null,
    "comment_preview": null,
    "link": "http://i.imgur.com/NBVf17d.jpg"
  },
  {
    "id": "dt1t7dA",
    "title": null,
    "description": null,
    "type": "image/jpeg",
    "width": 3456,
    "height": 4608,
    "size": 2793556,
    "account_url": null,
    "account_id": null,
    "comment_preview": null,
    "link": "http://i.imgur.com/dt1t7dA.jpg"
  },
  {
    "id": "aOtyepo",
    "title": null,
    "description": null,
    "type": "image/jpeg",
    "width": 3456,
    "height": 4608,
    "size": 2754029,
    "account_url": null,
    "account_id": null,
    "comment_preview": null,
    "link": "http://i.imgur.com/aOtyepo.jpg"
  }
]